<?xml version="1.0" encoding="UTF-8"?>
<widget name="GraphOne" id="ManualLayout/Widgets/GraphOne"
		spec="1.0" width="200" height="150" jsClass="Widgets.GraphOne"
		xmlns="http://openajax.org/metadata">

	<require type="javascript"><![CDATA[
	if (typeof(Widgets) == "undefined") {
		Widgets = {};
	}

	Widgets.GraphOne = function() {};
	
	Widgets.GraphOne.prototype.onLoad = function() {
		// maybe do something
	};
	]]></require>

	<require type="image" src="widgets/graph1.jpg" />

    <content>
		<![CDATA[
		<img src="widgets/graph1.jpg" width="100%" height="100%" alt="" />
		]]>
    </content>
    
	<categories>
    	<category name="Visualization" />
    </categories>
</widget>
